bridge/__init__.py
bridge/exec.py
bridge/result.py
bridge/contracts/__init__.py
bridge/contracts/base.py
bridge/contracts/detection_box.py
bridge/contracts/embed.py
bridge/utils/__init__.py
bridge/utils/globals.py
ultralyticspromax-0.0.1.dist-info/METADATA
ultralyticspromax-0.0.1.dist-info/WHEEL
ultralyticspromax-0.0.1.dist-info/top_level.txt
ultralyticspromax-0.0.1.dist-info/RECORD
